piradon/__init__.py
piradon/__version__.py
piradon/iradon.py
piradon-1.0.1.dist-info/LICENSE.txt
piradon-1.0.1.dist-info/METADATA
piradon-1.0.1.dist-info/WHEEL
piradon-1.0.1.dist-info/top_level.txt
piradon-1.0.1.dist-info/RECORD
